README.rst
setup.py
sweeper/__init__.py
sweeper/sweeper.py
sweeper.egg-info/PKG-INFO
sweeper.egg-info/SOURCES.txt
sweeper.egg-info/dependency_links.txt
sweeper.egg-info/entry_points.txt
sweeper.egg-info/requires.txt
sweeper.egg-info/top_level.txt
test/test_sweeper.py