Metadata-Version: 1.1
Name: sweeper
Version: 0.5.0
Summary: Find duplicate files and perform action.
Home-page: https://github.com/darko-poljak/sweeper
Author: Darko Poljak
Author-email: darko.poljak@gmail.com
License: GPLv3
Download-URL: https://github.com/darko-poljak/sweeper
Keywords: find duplicate files
Platform: OS Independent
Classifier: Development Status :: 4 - Beta
Classifier: License :: OSI Approved :: GNU General Public License v3 (GPLv3)
Classifier: Operating System :: OS Independent
Classifier: Topic :: Software Development :: Libraries :: Python Modules
